MANIFEST.in
README.rst
setup.py
sgsclient/__init__.py
sgsclient.egg-info/PKG-INFO
sgsclient.egg-info/SOURCES.txt
sgsclient.egg-info/dependency_links.txt
sgsclient.egg-info/not-zip-safe
sgsclient.egg-info/top_level.txt
sgsclient/example/__init__.py
sgsclient/example/tictactoe/__init__.py
sgsclient/example/tictactoe/manual.py
sgsclient/example/tictactoe/simple.py