Metadata-Version: 1.0
Name: sgsclient
Version: 0.1.0
Summary: The python client library for the Stratum Game Server.
Home-page: https://github.com/stratumgs/stratumgs-python-client
Author: David Korhumel
Author-email: dpk2442@gmail.com
License: MIT
Keywords: sgsclient
Platform: UNKNOWN
